{
    "DrillTool.EnergyCostLabel": "Consumo de energía (taladro de mano)",
    "DrillTool.EnergyCostTooltip": "Consumo de batería por cada «golpe» en un depósito de recursos.\nSe necesitan hasta 320 golpes para destruir completamente un depósito.\nLa energía solo se consume al minar depósitos grandes de recursos.",
	
    "DrillTool.HitIntervalLabel": "Intervalo de golpes (taladro de mano)",
    "DrillTool.HitIntervalTooltip": "Intervalo entre golpes en un depósito de recursos.\nUn valor menor es más rápido.\nSi usas el valor por defecto, la velocidad igualará la del brazo taladro del Prawn Suit.",
	
    "DrillTool": "Taladro de mano",
    "Tooltip_DrillTool": "Herramienta portátil de minería para extraer grandes depósitos de recursos."
}

